pytest_patch.py
pytest_patch-0.2.0.dist-info/LICENSE
pytest_patch-0.2.0.dist-info/METADATA
pytest_patch-0.2.0.dist-info/WHEEL
pytest_patch-0.2.0.dist-info/entry_points.txt
pytest_patch-0.2.0.dist-info/top_level.txt
pytest_patch-0.2.0.dist-info/RECORD
