Metadata-Version: 2.1
Name: pytest-patch
Version: 0.2.0
Summary: An automagic `patch` fixture that can patch objects directly or by name.
Home-page: https://github.com/megawidget/pytest-patch
Author: Igor Kaplounenko
Author-email: megawidget@gmail.com
Maintainer: Igor Kaplounenko
Maintainer-email: megawidget@gmail.com
License: MIT
Classifier: Development Status :: 3 - Alpha
Classifier: Framework :: Pytest
Classifier: Intended Audience :: Developers
Classifier: Topic :: Software Development :: Testing
Classifier: Programming Language :: Python
Classifier: Programming Language :: Python :: 3
Classifier: Programming Language :: Python :: 3.7
Classifier: Programming Language :: Python :: 3.8
Classifier: Programming Language :: Python :: 3.9
Classifier: Programming Language :: Python :: 3.10
Classifier: Programming Language :: Python :: 3.11
Classifier: Programming Language :: Python :: 3 :: Only
Classifier: Programming Language :: Python :: Implementation :: CPython
Classifier: Programming Language :: Python :: Implementation :: PyPy
Classifier: Operating System :: OS Independent
Classifier: License :: OSI Approved :: MIT License
Requires-Python: >=3.7
License-File: LICENSE
Requires-Dist: pytest (>=7.0.0)
Requires-Dist: mock
